Metadata-Version: 2.1
Name: covidwrapper
Version: 0.0.1
Summary: A Python wrapper for the covid19 API
Home-page: https://github.com/damildrizzy/pyvid
Author: Samuel Adekoya
Author-email: damiloladrizzy@yahoo.com
License: UNKNOWN
Platform: UNKNOWN
Classifier: Programming Language :: Python :: 3
Classifier: License :: OSI Approved :: MIT License
Classifier: Operating System :: OS Independent
Requires-Python: >=3.6
